MANIFEST.in
README.rst
setup.py
randomium/__init__.py
randomium/command_line.py
randomium.egg-info/PKG-INFO
randomium.egg-info/SOURCES.txt
randomium.egg-info/dependency_links.txt
randomium.egg-info/entry_points.txt
randomium.egg-info/not-zip-safe
randomium.egg-info/pbr.json
randomium.egg-info/top_level.txt