Metadata-Version: 1.1
Name: randomium
Version: 0.1
Summary: Tools for generating random things.
Home-page: http://github.com/jachin/randomium
Author: Jachin Rupe
Author-email: jachin@jachin.rupe.name
License: MIT
Platform: UNKNOWN
Classifier: Development Status :: 5 - Production/Stable
Classifier: License :: OSI Approved :: MIT License
Classifier: Programming Language :: Python :: 2.7
Classifier: Topic :: Software Development :: Testing
